dnsdb_getdns-0.1.2b2.dist-info/DESCRIPTION.rst
dnsdb_getdns-0.1.2b2.dist-info/METADATA
dnsdb_getdns-0.1.2b2.dist-info/RECORD
dnsdb_getdns-0.1.2b2.dist-info/WHEEL
dnsdb_getdns-0.1.2b2.dist-info/entry_points.txt
dnsdb_getdns-0.1.2b2.dist-info/metadata.json
dnsdb_getdns-0.1.2b2.dist-info/top_level.txt
getdns/__init__.py
