Metadata-Version: 2.0
Name: dnsdb-getdns
Version: 0.1.2b2
Summary: Query DNS records from dnsdb.io
Home-page: http://getdns.dnsdb.io
Author: DnsDB Team
Author-email: team@dnsdb.io
License: BSD License
Platform: UNKNOWN
Classifier: Development Status :: 4 - Beta
Classifier: Environment :: Console
Classifier: License :: OSI Approved :: BSD License
Classifier: Natural Language :: Chinese (Simplified)
Classifier: Operating System :: OS Independent
Classifier: Programming Language :: Python
Classifier: Programming Language :: Python :: 2.7
Classifier: Programming Language :: Python :: 3.3
Classifier: Programming Language :: Python :: 3.4
Classifier: Programming Language :: Python :: 3.5
Classifier: Programming Language :: Python :: 3.6
Requires-Python: >=2.7, !=3.0.*, !=3.1.*, !=3.2.*, <4
Requires-Dist: colorama
Requires-Dist: dnsdb-python-sdk (>=0.1.2b2)
Requires-Dist: iptools
Requires-Dist: setuptools
Requires-Dist: progress
